{
  "status": {
    "code": "OK",
    "comment": "http://permits.cloudapp.net/SolutionAdmin/getUserInfo"
  },
  "content": {
    "id": "ADMIN",
    "value": "ADMIN",
    "firstName": "Ella",
    "lastName": "Cunningham",
    "fullName": "Ella Cunningham",
    "serviceProviderCode": "BPTDEV",
    "department": {
      "id": "BPTDEV-BUILDING-NA-NA-NA-NA-NA",
      "serviceProviderCode": "BPTDEV",
      "group": "NA",
      "office": "NA",
      "bureau": "NA",
      "section": "NA",
      "division": "NA",
      "agency": "BUILDING",
      "text": "Building Department",
      "value": "BPTDEV/BUILDING/NA/NA/NA/NA/NA"
    }
  }
}